cxxtea.cp37-win32.pyd
cxxtea-1.0.7.dist-info/LICENSE
cxxtea-1.0.7.dist-info/METADATA
cxxtea-1.0.7.dist-info/WHEEL
cxxtea-1.0.7.dist-info/top_level.txt
cxxtea-1.0.7.dist-info/RECORD
